users/.git/config
users/.git/description
users/.git/FETCH_HEAD
users/.git/HEAD
users/.git/hooks/applypatch-msg.sample
users/.git/hooks/commit-msg.sample
users/.git/hooks/fsmonitor-watchman.sample
users/.git/hooks/post-update.sample
users/.git/hooks/pre-applypatch.sample
users/.git/hooks/pre-commit.sample
users/.git/hooks/pre-merge-commit.sample
users/.git/hooks/pre-push.sample
users/.git/hooks/pre-rebase.sample
users/.git/hooks/pre-receive.sample
users/.git/hooks/prepare-commit-msg.sample
users/.git/hooks/push-to-checkout.sample
users/.git/hooks/update.sample
users/.git/index
users/.git/info/exclude
users/.git/logs/HEAD
users/.git/logs/refs/heads/main
users/.git/logs/refs/remotes/origin/HEAD
users/.git/logs/refs/remotes/origin/main
users/.git/objects/9e/75c0756bf63291533f935a07862384abef300b
users/.git/objects/a0/c4d50a374cc3d3678338af0fcc272431a25b05
users/.git/objects/d3/f5f0af4c4c16c4c77a6b3cb3db6a1fd237f716
users/.git/objects/pack/pack-77a171cffe7147c6037a15847119d2105ca7efd5.idx
users/.git/objects/pack/pack-77a171cffe7147c6037a15847119d2105ca7efd5.pack
users/.git/ORIG_HEAD
users/.git/packed-refs
users/.git/refs/heads/main
users/.git/refs/remotes/origin/HEAD
users/.git/refs/remotes/origin/main
users/.gitignore
users/__init__.py
users/admin.py
users/apps.py
users/forms.py
users/LICENSE
users/migrations/__init__.py
users/mixins.py
users/models.py
users/permissions.py
users/README.md
users/routers.py
users/serializers.py
users/tests.py
users/urls.py
users/views.py
users/viewsets.py
dj_users-0.1.1.dist-info/METADATA
dj_users-0.1.1.dist-info/WHEEL
dj_users-0.1.1.dist-info/RECORD
